chorder/__init__.py
chorder/acchorder.py
chorder/chord.py
chorder/dechorder.py
chorder/schorer.py
chorder/timepoints.py
chorder-0.1.4.dist-info/LICENSE
chorder-0.1.4.dist-info/METADATA
chorder-0.1.4.dist-info/WHEEL
chorder-0.1.4.dist-info/top_level.txt
chorder-0.1.4.dist-info/RECORD
