Metadata-Version: 2.1
Name: chorder
Version: 0.1.4
Summary: A chord identifier and harmonizer for MIDI files
Home-page: https://github.com/joshuachang2311/chorder
Author: Joshua Chang
Author-email: chchang6@illinois.edu
License: UNKNOWN
Platform: UNKNOWN
Classifier: Programming Language :: Python :: 3
Classifier: License :: OSI Approved :: MIT License
Classifier: Operating System :: OS Independent
Requires-Python: >=3.6
License-File: LICENSE
Requires-Dist: numpy
Requires-Dist: miditoolkit
